freqsignals_client
