Metadata-Version: 2.1
Name: freqsignals-client
Version: 0.1.1
Summary: FreqSignals Client for Python
Home-page: https://github.com/freqsignals/freqsignals-client
Author: Matt Ferrante
Author-email: matt@freqsignals.com
License: MIT
Platform: UNKNOWN
